Metadata-Version: 2.0
Name: jpt-templated-docs
Version: 0.4.0
Summary: Generate PDF, MS Word and Excel documents from templates in Django.
Home-page: https://github.com/jptd/templated-docs
Author: Jewel Paymentech
Author-email: jafnee.jesmee@jewelpaymentech.com
License: MIT license
Keywords: templateddocs
Platform: UNKNOWN
Classifier: Development Status :: 2 - Pre-Alpha
Classifier: Intended Audience :: Developers
Classifier: License :: OSI Approved :: MIT License
Classifier: Natural Language :: English
Classifier: Programming Language :: Python :: 3
Classifier: Programming Language :: Python :: 3.6
Classifier: Programming Language :: Python :: 3.7
Requires-Dist: billiard (<3.6.0,>=3.5.0.2)
Requires-Dist: django (<3.0.0)
Requires-Dist: pylokit (==0.8.1)
